{
  "hash": "5d8d84d99afc74166d4db976b81e23a0",
  "result": {
    "markdown": "---\ntitle: \"Quarto in depth\"\nformat: revealjs\nexecute: \n  eval: true\n---\n\n\n## Chunk options\n\nIn your Quarto document, you saw\n\n````\n```{{r}}\n#| echo: false\n2 * 2\n```\n````\n\n## Chunk options\n\nSome of the ones I find myself using most often:\n\n\n::: {.cell hash='07-quarto2_cache/revealjs/unnamed-chunk-1_e5329c398241eb1d073138472d457e4a'}\n\n````{.cell-code}\n```{{r}}\n#| eval: false\n#| error: true\n#| cache: true\n#| warning: false\n#| message: false\nx <- 3\n```\n````\n:::\n\n\nAlso `echo` (can't include above because it conflicts with my slide options!)\n\n## Chunks can produce figures or tables\n\n\n::: {#tbl-one .cell tbl-cap='This is a great table'}\n\n````{.cell-code}\n```{{r}}\n#| label: tbl-one\n#| tbl-cap: \"This is a great table\"\nknitr::kable(mtcars)\n```\n````\n\n::: {.cell-output-display}\n\n\n|                    |  mpg| cyl|  disp|  hp| drat|    wt|  qsec| vs| am| gear| carb|\n|:-------------------|----:|---:|-----:|---:|----:|-----:|-----:|--:|--:|----:|----:|\n|Mazda RX4           | 21.0|   6| 160.0| 110| 3.90| 2.620| 16.46|  0|  1|    4|    4|\n|Mazda RX4 Wag       | 21.0|   6| 160.0| 110| 3.90| 2.875| 17.02|  0|  1|    4|    4|\n|Datsun 710          | 22.8|   4| 108.0|  93| 3.85| 2.320| 18.61|  1|  1|    4|    1|\n|Hornet 4 Drive      | 21.4|   6| 258.0| 110| 3.08| 3.215| 19.44|  1|  0|    3|    1|\n|Hornet Sportabout   | 18.7|   8| 360.0| 175| 3.15| 3.440| 17.02|  0|  0|    3|    2|\n|Valiant             | 18.1|   6| 225.0| 105| 2.76| 3.460| 20.22|  1|  0|    3|    1|\n|Duster 360          | 14.3|   8| 360.0| 245| 3.21| 3.570| 15.84|  0|  0|    3|    4|\n|Merc 240D           | 24.4|   4| 146.7|  62| 3.69| 3.190| 20.00|  1|  0|    4|    2|\n|Merc 230            | 22.8|   4| 140.8|  95| 3.92| 3.150| 22.90|  1|  0|    4|    2|\n|Merc 280            | 19.2|   6| 167.6| 123| 3.92| 3.440| 18.30|  1|  0|    4|    4|\n|Merc 280C           | 17.8|   6| 167.6| 123| 3.92| 3.440| 18.90|  1|  0|    4|    4|\n|Merc 450SE          | 16.4|   8| 275.8| 180| 3.07| 4.070| 17.40|  0|  0|    3|    3|\n|Merc 450SL          | 17.3|   8| 275.8| 180| 3.07| 3.730| 17.60|  0|  0|    3|    3|\n|Merc 450SLC         | 15.2|   8| 275.8| 180| 3.07| 3.780| 18.00|  0|  0|    3|    3|\n|Cadillac Fleetwood  | 10.4|   8| 472.0| 205| 2.93| 5.250| 17.98|  0|  0|    3|    4|\n|Lincoln Continental | 10.4|   8| 460.0| 215| 3.00| 5.424| 17.82|  0|  0|    3|    4|\n|Chrysler Imperial   | 14.7|   8| 440.0| 230| 3.23| 5.345| 17.42|  0|  0|    3|    4|\n|Fiat 128            | 32.4|   4|  78.7|  66| 4.08| 2.200| 19.47|  1|  1|    4|    1|\n|Honda Civic         | 30.4|   4|  75.7|  52| 4.93| 1.615| 18.52|  1|  1|    4|    2|\n|Toyota Corolla      | 33.9|   4|  71.1|  65| 4.22| 1.835| 19.90|  1|  1|    4|    1|\n|Toyota Corona       | 21.5|   4| 120.1|  97| 3.70| 2.465| 20.01|  1|  0|    3|    1|\n|Dodge Challenger    | 15.5|   8| 318.0| 150| 2.76| 3.520| 16.87|  0|  0|    3|    2|\n|AMC Javelin         | 15.2|   8| 304.0| 150| 3.15| 3.435| 17.30|  0|  0|    3|    2|\n|Camaro Z28          | 13.3|   8| 350.0| 245| 3.73| 3.840| 15.41|  0|  0|    3|    4|\n|Pontiac Firebird    | 19.2|   8| 400.0| 175| 3.08| 3.845| 17.05|  0|  0|    3|    2|\n|Fiat X1-9           | 27.3|   4|  79.0|  66| 4.08| 1.935| 18.90|  1|  1|    4|    1|\n|Porsche 914-2       | 26.0|   4| 120.3|  91| 4.43| 2.140| 16.70|  0|  1|    5|    2|\n|Lotus Europa        | 30.4|   4|  95.1| 113| 3.77| 1.513| 16.90|  1|  1|    5|    2|\n|Ford Pantera L      | 15.8|   8| 351.0| 264| 4.22| 3.170| 14.50|  0|  1|    5|    4|\n|Ferrari Dino        | 19.7|   6| 145.0| 175| 3.62| 2.770| 15.50|  0|  1|    5|    6|\n|Maserati Bora       | 15.0|   8| 301.0| 335| 3.54| 3.570| 14.60|  0|  1|    5|    8|\n|Volvo 142E          | 21.4|   4| 121.0| 109| 4.11| 2.780| 18.60|  1|  1|    4|    2|\n\n\n:::\n:::\n\n\n## Chunks can produce figures or tables\n\n\n::: {.cell}\n\n````{.cell-code}\n```{{r}}\n#| label: fig-hist\n#| fig-cap: \"This is a histogram\"\nhist(rnorm(100))\n```\n````\n\n::: {.cell-output-display}\n![This is a histogram](07-quarto2_files/figure-revealjs/fig-hist-1.png){#fig-hist width=960}\n:::\n:::\n\n\n## Cross-referencing\n\nYou can then refer to those with `@tbl-one` and `@fig-hist` and the Table and Figure ordering will be correct (and linked)\n\n::: larger-code\n```         \n@fig-hist contains a histogram and @tbl-one a table.\n```\n:::\n\ngets printed as:\n\n@fig-hist contains a histogram and @tbl-one a table.\n\n## Inline R\n\nI often create a list of stats that I want to report in a manuscript:\n\n\n::: {.cell}\n\n```{.r .cell-code}\nstats <- list(n = nrow(data),\n              mean_age = mean(data$age))\n```\n:::\n\n\nI can then print these numbers in the text with:\n\n\n::: {.cell}\n\n:::\n\n\nThere were `` `r stats$n` `` participants with a mean age of `` `r stats$mean_age` ``.\n\nwhich turns into:\n\nThere were 1123 participants with a mean age of 43.5.\n",
    "supporting": [],
    "filters": [
      "rmarkdown/pagebreak.lua"
    ],
    "includes": {
      "include-after-body": [
        "\n<script>\n  // htmlwidgets need to know to resize themselves when slides are shown/hidden.\n  // Fire the \"slideenter\" event (handled by htmlwidgets.js) when the current\n  // slide changes (different for each slide format).\n  (function () {\n    // dispatch for htmlwidgets\n    function fireSlideEnter() {\n      const event = window.document.createEvent(\"Event\");\n      event.initEvent(\"slideenter\", true, true);\n      window.document.dispatchEvent(event);\n    }\n\n    function fireSlideChanged(previousSlide, currentSlide) {\n      fireSlideEnter();\n\n      // dispatch for shiny\n      if (window.jQuery) {\n        if (previousSlide) {\n          window.jQuery(previousSlide).trigger(\"hidden\");\n        }\n        if (currentSlide) {\n          window.jQuery(currentSlide).trigger(\"shown\");\n        }\n      }\n    }\n\n    // hookup for slidy\n    if (window.w3c_slidy) {\n      window.w3c_slidy.add_observer(function (slide_num) {\n        // slide_num starts at position 1\n        fireSlideChanged(null, w3c_slidy.slides[slide_num - 1]);\n      });\n    }\n\n  })();\n</script>\n\n"
      ]
    },
    "engineDependencies": {},
    "preserve": {},
    "postProcess": true
  }
}